s2cell/__init__.py
s2cell/s2cell.py
s2cell-1.8.0.dist-info/LICENSE
s2cell-1.8.0.dist-info/METADATA
s2cell-1.8.0.dist-info/WHEEL
s2cell-1.8.0.dist-info/top_level.txt
s2cell-1.8.0.dist-info/RECORD
