Metadata-Version: 2.1
Name: s2cell
Version: 1.8.0
Summary: Minimal Python S2 Geometry cell ID, token and lat/lon conversion library
Home-page: https://docs.s2cell.aliddell.com
Download-URL: https://pypi.python.org/pypi/s2cell
Author: Adam Liddell
Author-email: s2cell@aliddell.com
Project-URL: Documentation, https://docs.s2cell.aliddell.com
Project-URL: Source Code, https://github.com/aaliddell/s2cell
Classifier: Intended Audience :: Developers
Classifier: Intended Audience :: Information Technology
Classifier: Intended Audience :: Science/Research
Classifier: Intended Audience :: Telecommunications Industry
Classifier: License :: OSI Approved :: Apache Software License
Classifier: Operating System :: OS Independent
Classifier: Programming Language :: Python :: 3 :: Only
Classifier: Topic :: Scientific/Engineering
Classifier: Topic :: Scientific/Engineering :: GIS
Classifier: Topic :: Software Development :: Libraries
Classifier: Topic :: Software Development :: Libraries :: Python Modules
Requires-Python: >=3.7
License-File: LICENSE
Provides-Extra: dev
Requires-Dist: furo ==2023.9.10 ; extra == 'dev'
Requires-Dist: nox ~=2023.4.22 ; extra == 'dev'
Requires-Dist: pytest ~=7.4.3 ; extra == 'dev'
Requires-Dist: pytest-cov ~=4.1.0 ; extra == 'dev'
Requires-Dist: pytest-instafail ~=0.5.0 ; extra == 'dev'
Requires-Dist: pytest-xdist ~=3.3.1 ; extra == 'dev'
Requires-Dist: ruff ~=0.1.6 ; extra == 'dev'
Requires-Dist: Sphinx ~=7.2.6 ; extra == 'dev'
Requires-Dist: sphinx-notfound-page ~=1.0.0 ; extra == 'dev'
Requires-Dist: sphinx-sitemap ==2.5.1 ; extra == 'dev'
